CHANGES.txt
LICENSE.txt
MANIFEST.in
README.txt
dotconfig.py
setup.py
DotConfig.egg-info/PKG-INFO
DotConfig.egg-info/SOURCES.txt
DotConfig.egg-info/dependency_links.txt
DotConfig.egg-info/top_level.txt
test/__init__.py
test/test_dotconfig.py