Metadata-Version: 1.0
Name: DotConfig
Version: 0.1.1
Summary: A simpler way to read configuration files.
Home-page: http://github.com/frawgie/dotconfig
Author: Jonas Ericsson
Author-email: jonas@agilefrog.se
License: LICENSE.txt
Platform: UNKNOWN
